django_nomad/__init__.py
django_nomad/git/__init__.py
django_nomad/git/exceptions.py
django_nomad/git/install_hook.py
django_nomad/git/utils.py
django_nomad/management/__init__.py
django_nomad/management/utils.py
django_nomad/management/commands/__init__.py
django_nomad/management/commands/check_nomad_migrations.py
django_nomad/management/commands/install_nomad_git_hook.py
django_nomad/migration/__init__.py
django_nomad/migration/utils.py
django_nomad-0.1.2.dist-info/LICENSE
django_nomad-0.1.2.dist-info/METADATA
django_nomad-0.1.2.dist-info/WHEEL
django_nomad-0.1.2.dist-info/top_level.txt
django_nomad-0.1.2.dist-info/RECORD
